{"version": "1", "message": "ERROR: Hidden Testcases server unreachable.", "problem_id": "ads2_m12_a1_1", "user_id": "harinath1314", "score": {"sample": {"0": {"execution_time": 0.3225698471069336, "passed": true}, "1": {"execution_time": 0.315654993057251, "passed": true}, "2": {"execution_time": 0.22707796096801758, "passed": true}, "3": {"execution_time": 0.22692394256591797, "passed": true}, "4": {"execution_time": 0.2269589900970459, "passed": true}, "5": {"execution_time": 0.22994589805603027, "passed": true}}}, "check_style_score": "0/1"}